{
    "/js/app.js": "/js/app.js",
    "/css/app.css": "/css/app.css",
    "/js/app.5d81433b26e8a7f93ea3.hot-update.js": "/js/app.5d81433b26e8a7f93ea3.hot-update.js",
    "/js/app.26f7b6164c2e8b2e7acf.hot-update.js": "/js/app.26f7b6164c2e8b2e7acf.hot-update.js",
    "/js/app.dbcdd6aca772d8ac8240.hot-update.js": "/js/app.dbcdd6aca772d8ac8240.hot-update.js",
    "/js/app.dd3c158278dbbb94ea57.hot-update.js": "/js/app.dd3c158278dbbb94ea57.hot-update.js",
    "/js/app.1dc83b3fdd0b86b2c7e5.hot-update.js": "/js/app.1dc83b3fdd0b86b2c7e5.hot-update.js",
    "/js/app.970e5d9275406f407cd2.hot-update.js": "/js/app.970e5d9275406f407cd2.hot-update.js",
    "/js/app.0f8bb3bc617887adebd5.hot-update.js": "/js/app.0f8bb3bc617887adebd5.hot-update.js"
}
